retrvtme/__init__.py
retrvtme/model.py
retrvtme/deconvolution/__init__.py
retrvtme/deconvolution/_callbacks.py
retrvtme/deconvolution/_dataset.py
retrvtme/deconvolution/_interface.py
retrvtme/deconvolution/_lightning_module.py
retrvtme/deconvolution/_nn.py
retrvtme/deconvolution/_utils.py
retrvtme/preprocessing/__init__.py
retrvtme/preprocessing/_bulk.py
retrvtme/preprocessing/_reference.py
retrvtme/simulation/__init__.py
retrvtme/simulation/_random.py
retrvtme/simulation/_simulator.py
retrvtme-0.1.0.dist-info/METADATA
retrvtme-0.1.0.dist-info/WHEEL
retrvtme-0.1.0.dist-info/licenses/LICENSE
retrvtme-0.1.0.dist-info/RECORD
